smp/__init__.py
smp/enumeration_management.py
smp/error.py
smp/exceptions.py
smp/file_management.py
smp/header.py
smp/image_management.py
smp/message.py
smp/os_management.py
smp/packet.py
smp/py.typed
smp/settings_management.py
smp/shell_management.py
smp/statistics_management.py
smp/user/__init__.py
smp/user/intercreate.py
smp/zephyr_management.py
smp-4.0.1.dist-info/LICENSE
smp-4.0.1.dist-info/METADATA
smp-4.0.1.dist-info/WHEEL
smp-4.0.1.dist-info/RECORD
