Metadata-Version: 2.1
Name: smp
Version: 4.0.1
Summary: Simple Management Protocol (SMP) for remotely managing MCU firmware
Home-page: https://github.com/JPHutchins/smp
License: Apache-2.0
Author: J.P. Hutchins
Author-email: jphutchins@gmail.com
Requires-Python: >=3.9
Classifier: License :: OSI Approved :: Apache Software License
Classifier: Programming Language :: Python :: 3
Classifier: Programming Language :: Python :: 3.9
Classifier: Programming Language :: Python :: 3.10
Classifier: Programming Language :: Python :: 3.11
Classifier: Programming Language :: Python :: 3.12
Classifier: Programming Language :: Python :: 3.13
Requires-Dist: cbor2 (>=5.5.1,<6.0.0)
Requires-Dist: crcmod (>=1.7,<2.0)
Requires-Dist: eval-type-backport (>=0.2.0,<0.3.0) ; python_version < "3.10"
Requires-Dist: pydantic (>=2.6,<3.0)
Project-URL: Documentation, https://jphutchins.github.io/smp/
Project-URL: Repository, https://github.com/JPHutchins/smp
